toolchain/__init__.py
toolchain/base/datetime_tools.py
toolchain/pants/register.py
toolchain/pants/version.py
toolchain/pants/auth/__init__.py
toolchain/pants/auth/client.py
toolchain/pants/auth/error.html
toolchain/pants/auth/favicon.png
toolchain/pants/auth/plugin.py
toolchain/pants/auth/rules.py
toolchain/pants/auth/server.py
toolchain/pants/auth/store.py
toolchain/pants/auth/subsystems.py
toolchain/pants/auth/success.html
toolchain/pants/auth/token.py
toolchain/pants/buildsense/client.py
toolchain/pants/buildsense/common.py
toolchain/pants/buildsense/converter.py
toolchain/pants/buildsense/local_store.py
toolchain/pants/buildsense/reporter.py
toolchain/pants/buildsense/rules.py
toolchain/pants/buildsense/state.py
toolchain/pants/buildsense/subsystems.py
toolchain/pants/common/errors.py
toolchain/pants/common/network.py
toolchain/pants/common/toolchain_setup.py
toolchain/util/constants.py
toolchain.pants.plugin-0.27.0.dist-info/METADATA
toolchain.pants.plugin-0.27.0.dist-info/WHEEL
toolchain.pants.plugin-0.27.0.dist-info/entry_points.txt
toolchain.pants.plugin-0.27.0.dist-info/namespace_packages.txt
toolchain.pants.plugin-0.27.0.dist-info/top_level.txt
toolchain.pants.plugin-0.27.0.dist-info/RECORD
