Metadata-Version: 2.1
Name: toolchain.pants.plugin
Version: 0.27.0
Summary: Toolchain Pants plugin.
Home-page: https://toolchain.com
Author: Toolchain Inc
Author-email: info@toolchain.com
License: Proprietary
Project-URL: Changelog, https://docs.toolchain.com/docs/toolchain-pants-plugin-changelog
Project-URL: Documentation, https://docs.toolchain.com/docs/getting-started-with-toolchain
Project-URL: Twitter, https://twitter.com/toolchainlabs
Classifier: Intended Audience :: Developers
Classifier: License :: Other/Proprietary License
Classifier: Operating System :: MacOS :: MacOS X
Classifier: Operating System :: POSIX :: Linux
Classifier: Programming Language :: Python
Classifier: Topic :: Software Development :: Build Tools
Classifier: Development Status :: 4 - Beta
Classifier: Environment :: Plugins
Classifier: Programming Language :: Python :: 3 :: Only
Classifier: Programming Language :: Python :: 3
Classifier: Programming Language :: Python :: 3.7
Classifier: Programming Language :: Python :: 3.8
Classifier: Programming Language :: Python :: 3.9
Requires-Python: >=3.7.2,<3.10
Requires-Dist: chardet (==5.0.0)
Requires-Dist: requests (>=2.28.1)
